django_tree_perm/__init__.py
django_tree_perm/apps.py
django_tree_perm/controller.py
django_tree_perm/exceptions.py
django_tree_perm/urls.py
django_tree_perm/utils.py
django_tree_perm/migrations/0001_initial.py
django_tree_perm/migrations/__init__.py
django_tree_perm/models/__init__.py
django_tree_perm/models/manager.py
django_tree_perm/models/tree.py
django_tree_perm/models/utils.py
django_tree_perm/static/tree_perm/favicon.ico
django_tree_perm/static/tree_perm/static/css/main.abc7f4f3.chunk.css
django_tree_perm/static/tree_perm/static/js/2.322ef1ec.chunk.js
django_tree_perm/static/tree_perm/static/js/main.54c27ceb.chunk.js
django_tree_perm/static/tree_perm/static/js/runtime-main.49cb3528.js
django_tree_perm/templates/tree_perm/main.html
django_tree_perm/views/__init__.py
django_tree_perm/views/base.py
django_tree_perm/views/tree.py
django_tree_perm-1.0.2.dist-info/LICENSE
django_tree_perm-1.0.2.dist-info/METADATA
django_tree_perm-1.0.2.dist-info/WHEEL
django_tree_perm-1.0.2.dist-info/top_level.txt
django_tree_perm-1.0.2.dist-info/RECORD
