Metadata-Version: 2.1
Name: django-tree-perm
Version: 1.0.2
Summary: django tree permisson
Home-page: https://github.com/SkylerHu/django-tree-perm.git
Author: SkylerHu
Author-email: skylerhu@qq.com
License: MIT Licence
Keywords: cmdb,tree,tree-permission
Platform: any
Classifier: Development Status :: 4 - Beta
Classifier: Intended Audience :: Developers
Classifier: License :: OSI Approved :: MIT License
Classifier: Programming Language :: Python :: 3
Classifier: Programming Language :: Python :: 3 :: Only
Classifier: Programming Language :: Python :: 3.6
Classifier: Programming Language :: Python :: 3.9
Classifier: Programming Language :: Python :: 3.10
Classifier: Programming Language :: Python :: 3.11
Classifier: Programming Language :: Python :: 3.12
Classifier: Programming Language :: Python :: Implementation :: CPython
Requires-Python: >=3.6
License-File: LICENSE
Requires-Dist: py-enum >=1.1.1
Requires-Dist: django >=3.0
